liana/__init__.py
liana/funcomics/__init__.py
liana/method/_Method.py
liana/method/__init__.py
liana/method/_liana_pipe.py
liana/method/_pipe_utils/__init__.py
liana/method/_pipe_utils/_aggregate.py
liana/method/_pipe_utils/_get_mean_perms.py
liana/method/_pipe_utils/_pre.py
liana/method/_pipe_utils/_reassemble_complexes.py
liana/method/sc/__init__.py
liana/method/sc/_cellphonedb.py
liana/method/sc/_connectome.py
liana/method/sc/_logfc.py
liana/method/sc/_natmi.py
liana/method/sc/_rank_aggregate.py
liana/method/sc/_singlecellsignalr.py
liana/multi/__init__.py
liana/plotting/__init__.py
liana/plotting/_dotplot.py
liana/resource/__init__.py
liana/resource/_resource_utils.py
liana/resource/_select_resource.py
liana/resource/omni_resource.csv
liana/testing/__init__.py
liana/testing/_sample_lrs.py
liana/tests/__init__.py
liana/tests/test_get_mean_perms.py
liana/tests/test_liana_pipe.py
liana/tests/test_methods.py
liana/tests/test_plotting.py
liana/tests/test_pre.py
liana/tests/test_rank_aggregate.py
liana/tests/data/aggregate_rank_rest.csv
liana/tests/data/all_defaults.csv
liana/tests/data/not_defaults.csv
liana_py-1.0.0.dist-info/LICENSE
liana_py-1.0.0.dist-info/METADATA
liana_py-1.0.0.dist-info/WHEEL
liana_py-1.0.0.dist-info/top_level.txt
liana_py-1.0.0.dist-info/RECORD
