Metadata-Version: 2.1
Name: liana-py
Version: 1.0.0
Summary: LIANA - a LIgand-receptor ANalysis frAmework
Home-page: https://github.com/saezlab/liana-py
Author: Daniel Dimitrov
Author-email: daniel.dimitrov@uni-heidelberg.de
Project-URL: Bug Tracker, https://github.com/saezlab/liana-py/issues
Classifier: Programming Language :: Python :: 3
Classifier: Operating System :: OS Independent
Requires-Python: >=3.7
License-File: LICENSE
Requires-Dist: numba
Requires-Dist: tqdm
Requires-Dist: pandas
Requires-Dist: anndata
Requires-Dist: scanpy
Requires-Dist: plotnine
